README.rst
setup.py
number2words/__init__.py
number2words.egg-info/PKG-INFO
number2words.egg-info/SOURCES.txt
number2words.egg-info/dependency_links.txt
number2words.egg-info/top_level.txt