Metadata-Version: 1.1
Name: number2words
Version: 0.1.3
Summary: Number2Words converts numbers to words according to Indian Numbering System.
Home-page: UNKNOWN
Author: hchockarprasad
Author-email: hchockarprasad@gmail.com
License: MIT License
Platform: UNKNOWN
Classifier: Operating System :: OS Independent
Classifier: Programming Language :: Python
Classifier: Programming Language :: Python :: 3.5
